CHANGES.txt
MANIFEST.in
README.rst
setup.py
isotoma/__init__.py
isotoma.recipe.apache.egg-info/PKG-INFO
isotoma.recipe.apache.egg-info/SOURCES.txt
isotoma.recipe.apache.egg-info/dependency_links.txt
isotoma.recipe.apache.egg-info/entry_points.txt
isotoma.recipe.apache.egg-info/namespace_packages.txt
isotoma.recipe.apache.egg-info/not-zip-safe
isotoma.recipe.apache.egg-info/requires.txt
isotoma.recipe.apache.egg-info/top_level.txt
isotoma/recipe/__init__.py
isotoma/recipe/apache/__init__.py
isotoma/recipe/apache/filter.py
isotoma/recipe/apache/htpasswd.py
isotoma/recipe/apache/logfilter.py
isotoma/recipe/apache/tests.py
isotoma/recipe/apache/templates/apache-ldap.cfg
isotoma/recipe/apache/templates/apache-maintenance.cfg
isotoma/recipe/apache/templates/apache-redirect.cfg
isotoma/recipe/apache/templates/apache-single.cfg
isotoma/recipe/apache/templates/apache-wsgi.cfg
isotoma/recipe/apache/templates/apache.cfg
isotoma/recipe/apache/templates/includes.cfg
isotoma/recipe/apache/templates/macros.cfg