Metadata-Version: 1.0
Name: isotoma.recipe.apache
Version: 0.6.15
Summary: Buildout recipes for apache.
Home-page: http://pypi.python.org/pypi/isotoma.recipe.apache
Author: Doug Winter
Author-email: doug.winter@isotoma.com
License: Apache Software License
Keywords: proxy buildout apache
Platform: UNKNOWN
Classifier: Framework :: Buildout
Classifier: Framework :: Buildout :: Recipe
Classifier: Intended Audience :: System Administrators
Classifier: Operating System :: POSIX
Classifier: License :: OSI Approved :: Apache Software License
